txgithub-15.0.0.dist-info/metadata.json
txgithub-15.0.0.dist-info/WHEEL
txgithub-15.0.0.dist-info/METADATA
txgithub-15.0.0.dist-info/RECORD
txgithub-15.0.0.dist-info/top_level.txt
txgithub-15.0.0.dist-info/DESCRIPTION.rst
txgithub-15.0.0.data/scripts/get-github-token
txgithub-15.0.0.data/scripts/gist
txgithub/constants.py
txgithub/api.py
txgithub/token.py
txgithub/__init__.py
txgithub/scripts/create_token.py
txgithub/scripts/gist.py
txgithub/scripts/__init__.py
