Metadata-Version: 2.0
Name: txgithub
Version: 15.0.0
Summary: GitHub API client implemented using Twisted.
Home-page: https://github.com/tomprince/txgithub
Author: Tom Prince
Author-email: tom.prince@ualberta.net
License: MIT
Platform: any
Classifier: Development Status :: 4 - Beta
Classifier: Framework :: Twisted
Classifier: Environment :: Web Environment
Classifier: Intended Audience :: Developers
Classifier: Intended Audience :: System Administrators
Classifier: License :: OSI Approved :: MIT License
Classifier: Operating System :: OS Independent
Classifier: Programming Language :: Python
Classifier: Topic :: Internet :: WWW/HTTP
Requires-Dist: twisted (>=12.3.0)
Requires-Dist: pyopenssl
